china_division/__init__.py
china_division/core.py
china_division/data.py
china_division/utils.py
china_division-2.0.dist-info/LICENSE.md
china_division-2.0.dist-info/METADATA
china_division-2.0.dist-info/WHEEL
china_division-2.0.dist-info/top_level.txt
china_division-2.0.dist-info/RECORD
