Metadata-Version: 2.1
Name: china-division
Version: 2.0
Summary: 中国行政区划查询工具
Home-page: https://github.com/zgxdxf/china-division
Author: wangxueming
Author-email: zgxdxf@hotmail.com
License: UNKNOWN
Keywords: china administrative division
Platform: UNKNOWN
Classifier: Programming Language :: Python :: 3
Classifier: License :: OSI Approved :: MIT License
Classifier: Operating System :: OS Independent
Requires-Python: >=3.6
